Metadata-Version: 2.1
Name: datagouv-dataeng-utils
Version: 0.0.3
Summary: Utils for data engineering team in data.gouv.fr
Home-page: https://github.com/etalab/datagouv-dataeng-utils
Author: Geoffrey Aldebert
Author-email: geoffrey.aldebert@data.gouv.fr
License: UNKNOWN
Project-URL: Bug Tracker, https://github.com/etalab/datagouv-dataeng-utils/issues
Platform: UNKNOWN
Classifier: Programming Language :: Python :: 3
Classifier: License :: OSI Approved :: MIT License
Classifier: Operating System :: OS Independent
Requires-Python: >=3.6
